DecryptLoginExamples/__init__.py
DecryptLoginExamples/client.py
DecryptLoginExamples/crawlers/__init__.py
DecryptLoginExamples/crawlers/bilibililottery/__init__.py
DecryptLoginExamples/crawlers/bilibililottery/bilibililottery.py
DecryptLoginExamples/crawlers/bilibiliupmonitor/__init__.py
DecryptLoginExamples/crawlers/bilibiliupmonitor/bilibiliupmonitor.py
DecryptLoginExamples/crawlers/bilibiliuservideos/__init__.py
DecryptLoginExamples/crawlers/bilibiliuservideos/bilibiliuservideos.py
DecryptLoginExamples/crawlers/clearqzone/__init__.py
DecryptLoginExamples/crawlers/clearqzone/clearqzone.py
DecryptLoginExamples/crawlers/cloud189signin/__init__.py
DecryptLoginExamples/crawlers/cloud189signin/cloud189signin.py
DecryptLoginExamples/crawlers/delallweibos/__init__.py
DecryptLoginExamples/crawlers/delallweibos/delallweibos.py
DecryptLoginExamples/crawlers/jdgoods/__init__.py
DecryptLoginExamples/crawlers/jdgoods/jdgoods.py
DecryptLoginExamples/crawlers/jingdongsnap/__init__.py
DecryptLoginExamples/crawlers/jingdongsnap/jingdongsnap.py
DecryptLoginExamples/crawlers/modifymihealthsteps/__init__.py
DecryptLoginExamples/crawlers/modifymihealthsteps/modifymihealthsteps.py
DecryptLoginExamples/crawlers/moocdl/__init__.py
DecryptLoginExamples/crawlers/moocdl/moocdl.py
DecryptLoginExamples/crawlers/neteaseclickplaylist/__init__.py
DecryptLoginExamples/crawlers/neteaseclickplaylist/neteaseclickplaylist.py
DecryptLoginExamples/crawlers/neteaseeveryday/__init__.py
DecryptLoginExamples/crawlers/neteaseeveryday/neteaseeveryday.py
DecryptLoginExamples/crawlers/neteaselistenleaderboard/__init__.py
DecryptLoginExamples/crawlers/neteaselistenleaderboard/neteaselistenleaderboard.py
DecryptLoginExamples/crawlers/neteasesignin/__init__.py
DecryptLoginExamples/crawlers/neteasesignin/neteasesignin.py
DecryptLoginExamples/crawlers/neteasesonglistdownloader/__init__.py
DecryptLoginExamples/crawlers/neteasesonglistdownloader/neteasesonglistdownloader.py
DecryptLoginExamples-0.1.1.dist-info/METADATA
DecryptLoginExamples-0.1.1.dist-info/WHEEL
DecryptLoginExamples-0.1.1.dist-info/top_level.txt
DecryptLoginExamples-0.1.1.dist-info/zip-safe
DecryptLoginExamples-0.1.1.dist-info/RECORD
