Metadata-Version: 2.1
Name: DecryptLoginExamples
Version: 0.1.1
Summary: DecryptLogin-examples: Some crawler examples for DecryptLogin.
Home-page: https://github.com/CharlesPikachu/DecryptLogin
Author: Charles
Author-email: charlesblwx@gmail.com
License: Apache License 2.0
Platform: UNKNOWN
Classifier: License :: OSI Approved :: Apache Software License
Classifier: Programming Language :: Python :: 3
Classifier: Intended Audience :: Developers
Classifier: Operating System :: OS Independent
Requires-Dist: DecryptLogin
Requires-Dist: tqdm
Requires-Dist: lxml
Requires-Dist: user-agent
Requires-Dist: prettytable
Requires-Dist: pyaudio
Requires-Dist: xmltodict
Requires-Dist: click
Requires-Dist: videofetch
Requires-Dist: pick
Requires-Dist: pyttsx3
